pyholecli/__init__.py
pyholecli/_version.py
pyholecli/exceptions.py
pyholecli/logging.py
pyholecli/main.py
pyholecli/models.py
pyholecli/services.py
pyholecli/settings.py
pyholecli/tasks.py
pyholecli/utils.py
pyholecli-0.0.1.dist-info/METADATA
pyholecli-0.0.1.dist-info/RECORD
pyholecli-0.0.1.dist-info/WHEEL
pyholecli-0.0.1.dist-info/entry_points.txt
pyholecli-0.0.1.dist-info/top_level.txt
