Metadata-Version: 2.1
Name: pyholecli
Version: 0.0.1
Summary: Remote management of a pi.hole instance.
Home-page: https://github.com/patrickjennings/pyholecli
Author: Patrick Jennings
Author-email: patrick@jenningsga.com
License: UNKNOWN
Platform: UNKNOWN
Classifier: Programming Language :: Python :: 3
Classifier: License :: OSI Approved :: MIT License
Classifier: Operating System :: OS Independent
Requires-Dist: fabric (==2.2.1)
